<?xml version="1.0" encoding="UTF-8"?>
<monster name="Insectoid Scout" nameDescription="a insectoid scout" race="venom" experience="150" speed="180" manacost="0">
  <health now="230" max="230"/>
  <look type="403" corpse="13514"/>
  <targetchange interval="5000" chance="8"/>
  <strategy attack="100" defense="0"/>
  <flags>
    <flag summonable="1"/>
    <flag attackable="1"/>
    <flag hostile="1"/>
    <flag illusionable="1"/>
    <flag convinceable="1"/>
    <flag pushable="1"/>
    <flag canpushitems="0"/>
    <flag canpushcreatures="0"/>
    <flag targetdistance="1"/>
    <flag staticattack="90"/>
    <flag runonhealth="0"/>
  </flags>
  <attacks>
    <attack name="melee" interval="2000" skill="30" attack="28" poison="3"/>	
  </attacks>
<immunities>
    <immunity invisible="1"/>
  </immunities>
<elements>
  <element earthPercent="-95"/>
  </elements>
<voices interval="5000" chance="10">
		<voice sentence="Klk! Klk! Chrrr! Chrrr!"/>					
</voices>
<loot>
    <item id="2148" countmax="69" chance1="33333" chancemax="0"/> -- Gold   
        <item id="7518" chance="3000"/> -- 
	 <item id="3964" chance="3000"/> --     
  </loot>   
</monster>
